OptiVisionNet/__init__.py
OptiVisionNet/gwo.py
OptiVisionNet/main.py
OptiVisionNet/model.py
OptiVisionNet/utils.py
OptiVisionNet-0.3.0.dist-info/METADATA
OptiVisionNet-0.3.0.dist-info/WHEEL
OptiVisionNet-0.3.0.dist-info/top_level.txt
OptiVisionNet-0.3.0.dist-info/RECORD
