Metadata-Version: 2.1
Name: OptiVisionNet
Version: 0.3.0
Summary: Usage example: from OptiVisionNet.model import CNN_BiLSTM_MLP
Author: Said Al Afghani Edsa
Author-email: saidalafghani.dumai@gmail.com
Requires-Python: >=3.6
Requires-Dist: torch
Requires-Dist: numpy
Requires-Dist: scikit-learn
Requires-Dist: tqdm
Requires-Dist: Pillow
